avilla/console/__init__.py
avilla/console/account.py
avilla/console/backend.py
avilla/console/element.py
avilla/console/perform/__init__.py
avilla/console/perform/action/activity.py
avilla/console/perform/action/message.py
avilla/console/perform/action/profile.py
avilla/console/perform/event/message.py
avilla/console/perform/message/deserialize.py
avilla/console/perform/message/serialize.py
avilla/console/protocol.py
avilla/console/service.py
avilla_console-0.2.0.dist-info/METADATA
avilla_console-0.2.0.dist-info/WHEEL
avilla_console-0.2.0.dist-info/licenses/LICENSE
avilla_console-0.2.0.dist-info/RECORD
