Metadata-Version: 2.1
Name: avilla-console
Version: 0.2.0
Summary: Avilla Console Protocol
Home-page: https://github.com/GraiaProject/Avilla
Author-Email: RF-Tar-Railt <rf_tar_railt@qq.com>
License: AGPL-3.0
Project-URL: Homepage, https://github.com/GraiaProject/Avilla
Project-URL: Repository, https://github.com/GraiaProject/Avilla
Requires-Python: >=3.9
Requires-Dist: nonechat<1.0.0,>=0.2.0
